Metadata-Version: 2.1
Name: py-apollo-config
Version: 1.1.2
Summary: python apollo config
Home-page: https://github.com/ztj1993/py-apollo-config
Author: ZhangTianJie
Author-email: ztj1993@gmail.com
License: MIT License
Keywords: apollo config
Platform: UNKNOWN
Requires-Dist: config-registry
Requires-Dist: py-apollo-client
